plantcv/__init__.py
plantcv/learn/__init__.py
plantcv/learn/cli.py
plantcv/learn/naive_bayes.py
plantcv/learn/train_kmeans.py
plantcv/parallel/__init__.py
plantcv/parallel/cli.py
plantcv/parallel/inspect_dataset.py
plantcv/parallel/job_builder.py
plantcv/parallel/multiprocess.py
plantcv/parallel/parsers.py
plantcv/parallel/process_results.py
plantcv/parallel/workflow_inputs.py
plantcv/parallel/workflowconfig.py
plantcv/plantcv/__init__.py
plantcv/plantcv/_debug.py
plantcv/plantcv/_helpers.py
plantcv/plantcv/_show_dataarray.py
plantcv/plantcv/apply_mask.py
plantcv/plantcv/auto_crop.py
plantcv/plantcv/background_subtraction.py
plantcv/plantcv/canny_edge_detect.py
plantcv/plantcv/classes.py
plantcv/plantcv/closing.py
plantcv/plantcv/color_palette.py
plantcv/plantcv/create_labels.py
plantcv/plantcv/crop.py
plantcv/plantcv/crop_position_mask.py
plantcv/plantcv/deprecation_warning.py
plantcv/plantcv/dilate.py
plantcv/plantcv/distance_transform.py
plantcv/plantcv/erode.py
plantcv/plantcv/fatal_error.py
plantcv/plantcv/fill.py
plantcv/plantcv/fill_holes.py
plantcv/plantcv/flip.py
plantcv/plantcv/floodfill.py
plantcv/plantcv/gaussian_blur.py
plantcv/plantcv/get_kernel.py
plantcv/plantcv/hist_equalization.py
plantcv/plantcv/image_add.py
plantcv/plantcv/image_fusion.py
plantcv/plantcv/image_subtract.py
plantcv/plantcv/invert.py
plantcv/plantcv/kmeans_classifier.py
plantcv/plantcv/laplace_filter.py
plantcv/plantcv/logical_and.py
plantcv/plantcv/logical_or.py
plantcv/plantcv/logical_xor.py
plantcv/plantcv/median_blur.py
plantcv/plantcv/naive_bayes_classifier.py
plantcv/plantcv/opening.py
plantcv/plantcv/output_mask_ori_img.py
plantcv/plantcv/plot_image.py
plantcv/plantcv/print_image.py
plantcv/plantcv/readbayer.py
plantcv/plantcv/readimage.py
plantcv/plantcv/report_size_marker_area.py
plantcv/plantcv/rgb2gray.py
plantcv/plantcv/rgb2gray_cmyk.py
plantcv/plantcv/rgb2gray_hsv.py
plantcv/plantcv/rgb2gray_lab.py
plantcv/plantcv/scharr_filter.py
plantcv-4.10.1.dist-info/licenses/LICENSE
plantcv-4.10.1.dist-info/METADATA
plantcv-4.10.1.dist-info/WHEEL
plantcv-4.10.1.dist-info/entry_points.txt
plantcv-4.10.1.dist-info/top_level.txt
plantcv-4.10.1.dist-info/RECORD
