Metadata-Version: 2.4
Name: plantcv
Version: 4.10.1
Summary: PlantCV: Plant phenotyping with computer vision
Author-email: PlantCV Team <plantcv@danforthcenter.org>
License: Mozilla Public License Version 2.0
Project-URL: Homepage, https://plantcv.org
Project-URL: Documentation, https://plantcv.readthedocs.io
Project-URL: Repository, https://github.com/danforthcenter/plantcv
Keywords: plantcv,plant phenotyping,image analysis,computer vision
Classifier: Programming Language :: Python :: 3
Classifier: License :: OSI Approved :: Mozilla Public License 2.0 (MPL 2.0)
Classifier: Intended Audience :: Science/Research
Classifier: Topic :: Scientific/Engineering :: Bio-Informatics
Classifier: Development Status :: 5 - Production/Stable
Requires-Python: >=3.8
License-File: LICENSE
Requires-Dist: matplotlib>=1.5
Requires-Dist: numpy>=2
Requires-Dist: pandas
Requires-Dist: python-dateutil
Requires-Dist: scipy<1.16
Requires-Dist: scikit-image>=0.19
Requires-Dist: scikit-learn
Requires-Dist: dask
Requires-Dist: dask-jobqueue
Requires-Dist: opencv-python
Requires-Dist: xarray>=2022.11.0
Requires-Dist: statsmodels
Requires-Dist: altair<6
Requires-Dist: vl-convert-python
Requires-Dist: nd2
Requires-Dist: flyr
Provides-Extra: test
Requires-Dist: pytest; extra == "test"
Requires-Dist: pytest-cov; extra == "test"
Dynamic: license-file
